tp_sql/main.py
tp_sql_09c77c38_19e1_42d9_886a_42a530ba9064-0.0.7.dist-info/METADATA
tp_sql_09c77c38_19e1_42d9_886a_42a530ba9064-0.0.7.dist-info/WHEEL
tp_sql_09c77c38_19e1_42d9_886a_42a530ba9064-0.0.7.dist-info/top_level.txt
tp_sql_09c77c38_19e1_42d9_886a_42a530ba9064-0.0.7.dist-info/RECORD
